pyevents/__init__.py
pyevents/events.py
tapis_pyevents-0.1.0.dist-info/METADATA
tapis_pyevents-0.1.0.dist-info/WHEEL
tapis_pyevents-0.1.0.dist-info/RECORD
