Metadata-Version: 2.1
Name: tapis-pyevents
Version: 0.1.0
Summary: Python package for developing event-engine plugins in Python.
Author: Joe Stubbs
Author-email: joestubbs5@gmail.com
Requires-Python: >=3.8,<4.0
Classifier: Programming Language :: Python :: 3
Classifier: Programming Language :: Python :: 3.8
Classifier: Programming Language :: Python :: 3.9
Classifier: Programming Language :: Python :: 3.10
Classifier: Programming Language :: Python :: 3.11
Requires-Dist: pyzmq (>=25.0.0,<26.0.0)
